{
  "subsection": "1.9 Summary",
  "summary": "This page explains that a system’s external input-output description can fail to capture its full internal structure, as illustrated by an example where an internal capacitor is invisible from the external terminals. It discusses how uncontrollable and unobservable subsystems lead external measurements to characterize only the controllable and observable portion of a system, and notes that such systems are undesirable in practice.",
  "keywords": [
    "summary",
    "external description",
    "internal description",
    "controllability",
    "observability",
    "uncontrollable systems",
    "unobservable systems",
    "input-output measurement",
    "subsystems",
    "system structure"
  ],
  "has_math": true,
  "page_type": "mixed",
  "book_page": "book-093",
  "figures": [
    {
      "fig_id": "Fig. 1.34",
      "top": 0.0636,
      "left": 0.0384,
      "bottom": 0.227,
      "right": 0.5677,
      "caption": "Fig. 1.34 A system that cannot be described by external measurements."
    },
    {
      "fig_id": "Fig. 1.35",
      "top": 0.4479,
      "left": 0.0822,
      "bottom": 0.5575,
      "right": 0.5654,
      "caption": "Fig. 1.35 Structures of uncontrollable and unobservable systems."
    }
  ]
}